treebased_synthetic_controls/__init__.py
treebased_synthetic_controls/synthetic_controls.py
treebased_synthetic_controls/tbsc.py
treebased_synthetic_controls/test.py
treebased_synthetic_controls/base/__init__.py
treebased_synthetic_controls/base/base_synthetic_controls.py
treebased_synthetic_controls/estimator/__init__.py
treebased_synthetic_controls/estimator/constrained_ols.py
treebased_synthetic_controls/utils/__init__.py
treebased_synthetic_controls/utils/bootstrap.py
treebased_synthetic_controls/utils/data.py
treebased_synthetic_controls/utils/exceptions.py
treebased_synthetic_controls/utils/sanity_check.py
treebased_synthetic_controls/utils/tools.py
treebased_synthetic_controls-0.1.12.dist-info/LICENSE
treebased_synthetic_controls-0.1.12.dist-info/METADATA
treebased_synthetic_controls-0.1.12.dist-info/WHEEL
treebased_synthetic_controls-0.1.12.dist-info/top_level.txt
treebased_synthetic_controls-0.1.12.dist-info/RECORD
